LICENSE.txt
MANIFEST.in
README.md
README_FOR_DEVELOPERS.md
setup.cfg
setup.py
binmapper/__init__.py
binmapper/types.py
binmapper.egg-info/PKG-INFO
binmapper.egg-info/SOURCES.txt
binmapper.egg-info/dependency_links.txt
binmapper.egg-info/not-zip-safe
binmapper.egg-info/requires.txt
binmapper.egg-info/top_level.txt
binmapper/codec/__init__.py
binmapper/codec/register.py
binmapper/parser/__init__.py
binmapper/parser/dump.py
binmapper/parser/grammar.py
binmapper/parser/helper.py
binmapper/parser/lexical_analyser.py
binmapper/parser/syntaxis_analyser.py
binmapper/parser/syntaxis_types.py
binmapper/parser/template_context.py
binmapper/parser/templates/__init__.py
binmapper/parser/templates/bintype.template
binmapper/tests/__init__.py
binmapper/tests/test_01_ctx.py
binmapper/tests/test_02_wisent.py
binmapper/tests/test_03_let_basic.py
binmapper/tests/test_04_parser_basic.py
binmapper/tests/test_05_basic.py
binmapper/tests/test_06_array.py
binmapper/tests/test_07_let.py
binmapper/tests/test_08_user.py
binmapper/tests/test_09_manual.py
binmapper/tests/test_10_codec.py
binmapper/tests/temp/__init__.py
binmapper/tests/temp/definition.py