Metadata-Version: 1.1
Name: binmapper
Version: 0.1a3
Summary: Domain Specific Language(DSL) for parsing and mapping binary data to python objects
Home-page: https://bitbucket.org/RedSkotina/binmapper
Author: RedSkotina
Author-email: red.skotina@gmail.com
License: 